pyusacycling/__init__.py
pyusacycling/__main__.py
pyusacycling/cli.py
pyusacycling/client.py
pyusacycling/exceptions.py
pyusacycling/models.py
pyusacycling/parser.py
pyusacycling/serializers.py
pyusacycling/test1.py
pyusacycling/utils.py
pyusacycling-0.1.4.dist-info/licenses/LICENSE
tests/__init__.py
tests/test_base_parser.py
tests/test_caching.py
tests/test_cli.py
tests/test_client.py
tests/test_csv_serializer.py
tests/test_event_details_parser.py
tests/test_event_list_parser.py
tests/test_exceptions.py
tests/test_json_serializer.py
tests/test_logging.py
tests/test_race_results_parser.py
tests/test_rate_limiting.py
pyusacycling-0.1.4.dist-info/METADATA
pyusacycling-0.1.4.dist-info/WHEEL
pyusacycling-0.1.4.dist-info/entry_points.txt
pyusacycling-0.1.4.dist-info/top_level.txt
pyusacycling-0.1.4.dist-info/RECORD
